nanoAPI/__init__.py
nanoAPI/app.py
nanoAPI/core/__init__.py
nanoAPI/core/errors.py
nanoAPI/core/run_manager.py
nanoAPI/db/__init__.py
nanoAPI/db/db.py
nanoAPI/db/model.py
nanoAPI/db/types.py
nanoAPI/handler/__init__.py
nanoAPI/handler/request.py
nanoAPI/handler/response.py
nanoAPI/handler/router.py
nanoAPI/handler/status.py
nanoAPI/utils/__init__.py
nanoAPI/utils/datastructures.py
nanoAPI/utils/logger.py
nanoAPI/utils/route_parser.py
nanoAPI/utils/tools.py
test/__init__.py
test/controllers.py
test/models.py
test/routes.py
nanoAPI-0.5.0.dist-info/LICENSE
nanoAPI-0.5.0.dist-info/METADATA
nanoAPI-0.5.0.dist-info/WHEEL
nanoAPI-0.5.0.dist-info/top_level.txt
nanoAPI-0.5.0.dist-info/RECORD
