Metadata-Version: 2.1
Name: nanoAPI
Version: 0.5.0
Summary: A nano web framework
Home-page: https://github.com/Nandan-unni/Nano
Author: Nandanunni A S
Author-email: asnqln@gmail.com
License: MIT
Platform: UNKNOWN
Classifier: License :: OSI Approved :: MIT License
Classifier: Programming Language :: Python :: 3
Classifier: Programming Language :: Python :: 3.7
Classifier: Operating System :: OS Independent
Requires-Python: >=3.6
Requires-Dist: colorama (==0.4.4)
Requires-Dist: gunicorn (==20.0.4)
